{"items":{"serializeList":[{"name":"hay","nr":9182.0},{"name":"wood","nr":43710.0},{"name":"carrot","nr":21873.0},{"name":"water","nr":5274.0},{"name":"pumpkin","nr":97739.0},{"name":"fertilizer","nr":9592.0},{"name":"weird_substance","nr":294.0},{"name":"bone","nr":22060.0},{"name":"power","nr":10990.59799998828},{"name":"cactus","nr":5704.0}]},"dockedFiles":[{"key":"bone","value":"energy"},{"key":"wood","value":"carrot"},{"key":"carrot","value":"pumpkin"},{"key":"movement","value":"util"},{"key":"pumpkin","value":"movement"},{"key":"reset","value":"console"},{"key":"energy","value":"wood"},{"key":"util","value":"general"}],"minimizedFiles":["bone","wood","carrot","general","harvest","movement","pumpkin","reset","util"],"openFilePositions":[{"key":"blueprint","value":{"x":884.7418212890625,"y":-484.0885009765625}},{"key":"bone","value":{"x":682.97509765625,"y":-814.684326171875}},{"key":"wood","value":{"x":682.97509765625,"y":-814.684326171875}},{"key":"carrot","value":{"x":682.97509765625,"y":-814.684326171875}},{"key":"console","value":{"x":40.201171875,"y":1079.0074462890625}},{"key":"Farm basic crop","value":{"x":1637.8736572265625,"y":778.724609375}},{"key":"general","value":{"x":-890.8306884765625,"y":199.6561279296875}},{"key":"harvest","value":{"x":-319.5137939453125,"y":185.54052734375}},{"key":"Make anything","value":{"x":1621.4688720703125,"y":121.3748779296875}},{"key":"movement","value":{"x":682.97509765625,"y":-814.684326171875}},{"key":"plant","value":{"x":-406.186767578125,"y":-905.6416015625}},{"key":"pumpkin","value":{"x":682.97509765625,"y":-814.684326171875}},{"key":"reset","value":{"x":682.97509765625,"y":-814.684326171875}},{"key":"router","value":{"x":-917.9683837890625,"y":-917.490234375}},{"key":"energy","value":{"x":682.97509765625,"y":-814.684326171875}},{"key":"cactus","value":{"x":-32.6947021484375,"y":-160.6527099609375}},{"key":"testing","value":{"x":242.75851440429688,"y":-972.6532592773438}},{"key":"docs0","value":{"x":-925.31005859375,"y":968.5689697265625}},{"key":"util","value":{"x":682.97509765625,"y":-814.684326171875}}],"openFileScrollPositions":[{"key":"blueprint","value":198.3584747314453},{"key":"bone","value":162.37606811523438},{"key":"wood","value":0.00079345703125},{"key":"carrot","value":100.00006103515625},{"key":"console","value":0.0},{"key":"Farm basic crop","value":206.38954162597657},{"key":"general","value":161.95401000976563},{"key":"harvest","value":0.00054931640625},{"key":"Make anything","value":692.8494262695313},{"key":"movement","value":1370.7728271484375},{"key":"plant","value":0.0018310546875},{"key":"pumpkin","value":321.180908203125},{"key":"reset","value":0.0},{"key":"router","value":438.18646240234377},{"key":"energy","value":0.0},{"key":"cactus","value":1723.0},{"key":"testing","value":0.000244140625},{"key":"util","value":0.00042724609375}],"openFileSizes":[{"key":"blueprint","value":{"x":0.0,"y":836.9523315429688}},{"key":"bone","value":{"x":0.0,"y":0.0}},{"key":"wood","value":{"x":0.0,"y":0.0}},{"key":"carrot","value":{"x":0.0,"y":0.0}},{"key":"console","value":{"x":0.0,"y":0.0}},{"key":"Farm basic crop","value":{"x":0.0,"y":0.0}},{"key":"general","value":{"x":0.0,"y":0.0}},{"key":"harvest","value":{"x":0.0,"y":0.0}},{"key":"Make anything","value":{"x":0.0,"y":0.0}},{"key":"movement","value":{"x":0.0,"y":980.8621215820313}},{"key":"plant","value":{"x":0.0,"y":0.0}},{"key":"pumpkin","value":{"x":0.0,"y":0.0}},{"key":"reset","value":{"x":0.0,"y":0.0}},{"key":"router","value":{"x":0.0,"y":454.052978515625}},{"key":"energy","value":{"x":0.0,"y":0.0}},{"key":"cactus","value":{"x":0.0,"y":0.0}},{"key":"testing","value":{"x":0.0,"y":680.7232666015625}},{"key":"docs0","value":{"x":900.0,"y":700.0}},{"key":"util","value":{"x":0.0,"y":0.0}}],"openDocPages":[{"key":"docs0","value":"docs/output.md"}],"unlocks":["grass_8","soil","harvest","pass","do_a_flip","grassland","hay","straw_hat","while","true","false","break","continue","loops","speed_7","can_harvest","if","else","elif","expand_7","move","north","south","east","west","wood","bush","entities","clear","plant","for","range","get_world_size","carrots_11","carrot","till","can_trade","trade","items","carrot_seed","and","or","not","operators","get_entity_type","get_ground_type","grounds","get_pos_x","get_pos_y","none","num_items","senses","print","quick_print","unlocks","str","debug","water","use_item","get_water","watering","variables","trees_8","tree","functions","def","return","global","pumpkins_6","pumpkin","pumpkin_seed","append","remove","pop","insert","len","list","lists","from","import","min","max","abs","random","utilities","dicts","sets","add","dict","set","dictionaries","get_time","get_tick_count","timing","fertilizer_2","weird_substance","hedge","treasure","gold","measure","mazes","get_cost","costs","sunflower_seed","sunflower","power","get_active_power","sunflowers","dinosaur","egg","bone","change_hat","hats","dinosaur_hat","apple","dinosaurs","cactus","swap","cactus_seed"],"version":2}